annadca/__init__.py
annadca/classes.py
annadca/cli.py
annadca/dataset.py
annadca/io.py
annadca/parser.py
annadca/plot.py
annadca/train.py
annadca/utils.py
annadca/rbm/__init__.py
annadca/rbm/binary/__init__.py
annadca/rbm/binary/classes.py
annadca/rbm/binary/grad.py
annadca/rbm/binary/init.py
annadca/rbm/binary/sampling.py
annadca/rbm/binary/statmech.py
annadca/rbm/binary/stats.py
annadca/rbm/categorical/__init__.py
annadca/rbm/categorical/classes.py
annadca/rbm/categorical/grad.py
annadca/rbm/categorical/init.py
annadca/rbm/categorical/sampling.py
annadca/rbm/categorical/statmech.py
annadca/scripts/__init__.py
annadca/scripts/train.py
annadca-0.2.1.dist-info/licenses/LICENSE
annadca-0.2.1.dist-info/METADATA
annadca-0.2.1.dist-info/WHEEL
annadca-0.2.1.dist-info/entry_points.txt
annadca-0.2.1.dist-info/top_level.txt
annadca-0.2.1.dist-info/RECORD
