Metadata-Version: 2.4
Name: annadca
Version: 0.2.1
Summary: Annotation Assisted Direct Coupling Analysis
Home-page: https://github.com/rossetl/annaDCA
Author: Lorenzo Rosset, Aurélien Decelle, Beatriz Seoane, Francesco Zamponi, Martin Weigt
Author-email: rosset.lorenzo@gmail.com
Maintainer: Lorenzo Rosset
Classifier: Programming Language :: Python :: 3
Classifier: License :: OSI Approved :: Apache Software License
Classifier: Operating System :: OS Independent
Requires-Python: >=3.10
License-File: LICENSE
Requires-Dist: adabmDCA>=0.7.0
Dynamic: author
Dynamic: author-email
Dynamic: classifier
Dynamic: description
Dynamic: description-content-type
Dynamic: home-page
Dynamic: license-file
Dynamic: maintainer
Dynamic: requires-dist
Dynamic: requires-python
Dynamic: summary
